oc_graphenricher/APIs/__init__.py
oc_graphenricher/APIs/stopwords-it.txt
oc_graphenricher/APIs/test_queryinterface.py
oc_graphenricher/__init__.py
oc_graphenricher/enricher/__init__.py
oc_graphenricher/instancematching/__init__.py
oc_graphenricher/instancematching/generate_test_graphset.py
oc_graphenricher/instancematching/matched.rdf.lock
oc_graphenricher/instancematching/provenance.rdf.lock
oc_graphenricher/instancematching/test_instancematching.py
oc_graphenricher/instancematching/test_merge_br.rdf
oc_graphenricher-0.2.5.dist-info/LICENSE
oc_graphenricher-0.2.5.dist-info/METADATA
oc_graphenricher-0.2.5.dist-info/WHEEL
oc_graphenricher-0.2.5.dist-info/entry_points.txt
oc_graphenricher-0.2.5.dist-info/RECORD
