Metadata-Version: 2.1
Name: oc-graphenricher
Version: 0.2.5
Summary: A tool to enrich any OCDM compliant Knowledge Graph, finding new identifiers and deduplicating entities
License: ISC
Author: Gabriele Pisciotta
Author-email: ga.pisciotta@gmail.com
Requires-Python: >=3.8,<4.0
Classifier: License :: OSI Approved
Classifier: Programming Language :: Python :: 3
Classifier: Programming Language :: Python :: 3.8
Classifier: Programming Language :: Python :: 3.9
Classifier: Programming Language :: Python :: 3.10
Classifier: Programming Language :: Python :: 3.11
Requires-Dist: levenshtein (>=0.22.0,<0.23.0)
Requires-Dist: networkx (==2.5)
Requires-Dist: oc-ocdm (==7.3.1)
Requires-Dist: python-levenshtein (==0.12.2)
Requires-Dist: rdflib (==6.3.2)
Requires-Dist: requests (==2.22.0)
Requires-Dist: requests-cache (==0.6.0)
Requires-Dist: tqdm (==4.47.0)
